fritchicrawler/__init__.py
fritchicrawler/fritchicrawler.py
fritchicrawler-0.1.5.dist-info/METADATA
fritchicrawler-0.1.5.dist-info/WHEEL
fritchicrawler-0.1.5.dist-info/RECORD
